nbforge/__init__.py
nbforge/chains.py
nbforge/cli.py
nbforge/converter.py
nbforge/groq_client.py
nbforge/logger.py
nbforge/parser.py
nbforge/writer.py
nbforge/utils/__init__.py
nbforge/utils/constants.py
nbforge/utils/prompts.yml
nbforge-0.1.11.dist-info/METADATA
nbforge-0.1.11.dist-info/WHEEL
nbforge-0.1.11.dist-info/entry_points.txt
nbforge-0.1.11.dist-info/top_level.txt
nbforge-0.1.11.dist-info/RECORD
